preprocessor_ml/__init__.py
preprocessor_ml-0.1.0.dist-info/METADATA
preprocessor_ml-0.1.0.dist-info/WHEEL
preprocessor_ml-0.1.0.dist-info/RECORD
